{
  "posts": [
    {
      "author": "gdfgdf",
      "title": "gfdgdf",
      "body_text": "<p>gdfgfdgdf</p>",
      "author_id": "3dfb12f1-64c1-4189-82f6-cec3cf2fc39d",
      "id": 1
    },
    {
      "author": "dfhkhjklj",
      "title": "fgdfg",
      "body_text": "<p>çkljçlkçkl</p>",
      "author_id": "57149c25-fb8b-4d22-b594-f80c879f1632",
      "id": 2
    },
    {
      "author": "gfdjh,",
      "title": "dfghfdgfd",
      "body_text": "<p>kjlkj</p>",
      "author_id": "337ab85d-5b2f-4e8b-bd27-59c8f2aea3f0",
      "id": 3
    },
    {
      "author": "fghfghgfhfgh",
      "title": "kjhkjhk",
      "body_text": "<p>hjkhjkhj</p>",
      "author_id": "474c921a-2fa8-4579-8bc1-4553ada22c01",
      "id": 4
    },
    {
      "author": "dfgdfgdf",
      "title": "gdfg",
      "body_text": "<p>gdfgfdg</p>",
      "author_id": "ee2c610f-272a-4f20-b244-cd0f01359c97",
      "id": 5
    }
  ]
}